galleryserve/__init__.py
galleryserve/admin.py
galleryserve/migrations/0001_initial.py
galleryserve/migrations/0002_gallery_random.py
galleryserve/migrations/0003_auto_20220125_1108.py
galleryserve/migrations/__init__.py
galleryserve/models.py
galleryserve/south_migrations/0001_initial.py
galleryserve/south_migrations/0002_auto__add_field_gallery_random.py
galleryserve/south_migrations/__init__.py
galleryserve/templatetags/__init__.py
galleryserve/templatetags/gallerytags.py
galleryserve/views.py
galleryserve-0.2.2.dist-info/WHEEL
galleryserve-0.2.2.dist-info/METADATA
galleryserve-0.2.2.dist-info/RECORD
