Metadata-Version: 2.1
Name: galleryserve
Version: 0.2.2
Summary: Adapted from imageserve to fit broader gallery needs such as video embedding and content for controls.
Home-page: https://github.com/ImaginaryLandscape/django-galleryserve
License: MIT
Author: Imagescape
Author-email: info@imagescape.com
Requires-Python: >=3.7,<4.0
Classifier: License :: OSI Approved :: MIT License
Classifier: Programming Language :: Python :: 3
Classifier: Programming Language :: Python :: 3.7
Classifier: Programming Language :: Python :: 3.8
Classifier: Programming Language :: Python :: 3.9
Requires-Dist: Pillow (>=9.1.1,<10.0.0)
